[
  {
    "id": 1,
    "name": "The revenant",
    "rate": "HIGH",
    "basePrice": 60.0,
    "dateTime": [
      2020,
      2,
      5,
      9,
      0
    ],
    "auditorium": {
      "id": 1,
      "name": "Blue hall",
      "seatsNumber": 500,
      "vipSeats": "25,26,27,28,29,30,31,32,33,34,35",
      "vipSeatsList": [
        25,
        26,
        27,
        28,
        29,
        30,
        31,
        32,
        33,
        34,
        35
      ]
    }
  },
  {
    "id": 2,
    "name": "Some event",
    "rate": "HIGH",
    "basePrice": 60.0,
    "dateTime": [
      2020,
      2,
      5,
      15,
      45
    ],
    "auditorium": {
      "id": 1,
      "name": "Blue hall",
      "seatsNumber": 500,
      "vipSeats": "25,26,27,28,29,30,31,32,33,34,35",
      "vipSeatsList": [
        25,
        26,
        27,
        28,
        29,
        30,
        31,
        32,
        33,
        34,
        35
      ]
    }
  },
  {
    "id": 3,
    "name": "TAT meeting",
    "rate": "HIGH",
    "basePrice": 60.0,
    "dateTime": [
      2020,
      2,
      5,
      21,
      18
    ],
    "auditorium": {
      "id": 1,
      "name": "Blue hall",
      "seatsNumber": 500,
      "vipSeats": "25,26,27,28,29,30,31,32,33,34,35",
      "vipSeatsList": [
        25,
        26,
        27,
        28,
        29,
        30,
        31,
        32,
        33,
        34,
        35
      ]
    }
  },
  {
    "id": 4,
    "name": "Epam's day",
    "rate": "HIGH",
    "basePrice": 90.0,
    "dateTime": [
      2020,
      2,
      5,
      21,
      18
    ],
    "auditorium": {
      "id": 2,
      "name": "Red hall",
      "seatsNumber": 800,
      "vipSeats": "25,26,27,28,29,30,31,32,33,34,35,75,76,77,78,79,80,81,82,83,84,85",
      "vipSeatsList": [
        25,
        26,
        27,
        28,
        29,
        30,
        31,
        32,
        33,
        34,
        35,
        75,
        76,
        77,
        78,
        79,
        80,
        81,
        82,
        83,
        84,
        85
      ]
    }
  },
  {
    "id": 5,
    "name": "BMTH concert",
    "rate": "HIGH",
    "basePrice": 150.0,
    "dateTime": [
      2020,
      2,
      5,
      21,
      18
    ],
    "auditorium": {
      "id": 3,
      "name": "Yellow hall",
      "seatsNumber": 1000,
      "vipSeats": "25,26,27,28,29,30,31,32,33,34,35,75,76,77,78,79,80,81,82,83,84,85,105,106,107,108,109,110,111,112,113,114,115",
      "vipSeatsList": [
        25,
        26,
        27,
        28,
        29,
        30,
        31,
        32,
        33,
        34,
        35,
        75,
        76,
        77,
        78,
        79,
        80,
        81,
        82,
        83,
        84,
        85,
        105,
        106,
        107,
        108,
        109,
        110,
        111,
        112,
        113,
        114,
        115
      ]
    }
  }
]